lusid/__init__.py
lusid/lusid.py
lusid/mac_db.py
lusid/message_client.py
lusid/read_messages.py
lusid/send_message.py
lusid/simple_message_client.py
lusid/imessage_reader/__init__.py
lusid/imessage_reader/cli.py
lusid/imessage_reader/common.py
lusid/imessage_reader/create_sqlite.py
lusid/imessage_reader/data_container.py
lusid/imessage_reader/fetch_data.py
lusid/imessage_reader/info.py
lusid/imessage_reader/write_excel.py
lusid/py_imessage/__init__.py
lusid/py_imessage/db_conn.py
lusid/py_imessage/imessage.py
lusid/py_imessage/osascript/check_imessage.js
lusid/py_imessage/osascript/send_message.js
lusid-1.0.10.dist-info/LICENSE
lusid-1.0.10.dist-info/METADATA
lusid-1.0.10.dist-info/WHEEL
lusid-1.0.10.dist-info/top_level.txt
lusid-1.0.10.dist-info/RECORD
