Metadata-Version: 2.1
Name: lusid
Version: 1.0.10
Summary: Self-hosted iMessage client (Twilio with blue bubbles)
Author-email: Yev Barkalov <yev@lsd.so>
Project-URL: Homepage, https://github.com/yevbar/lusid
Project-URL: Issues, https://github.com/yevbar/lusid/issues
Classifier: Programming Language :: Python :: 3
Classifier: License :: OSI Approved :: MIT License
Classifier: Operating System :: MacOS
Requires-Python: >=3.8
License-File: LICENSE
Requires-Dist: openpyxl >=3.1.3
Requires-Dist: pytz >=2024.1
